graspgraph/__init__.py
graspgraph/array.py
graspgraph/cli.py
graspgraph/color.py
graspgraph/database.py
graspgraph/dbergraph.py
graspgraph/digraph.py
graspgraph/figure.py
graspgraph/pdf.py
graspgraph/pivotgraph.py
graspgraph/statsgraph.py
graspgraph-0.3.4.dist-info/LICENSE
graspgraph-0.3.4.dist-info/METADATA
graspgraph-0.3.4.dist-info/WHEEL
graspgraph-0.3.4.dist-info/entry_points.txt
graspgraph-0.3.4.dist-info/top_level.txt
graspgraph-0.3.4.dist-info/RECORD
