Metadata-Version: 2.1
Name: graspgraph
Version: 0.3.4
Summary: Create easy-to-understand graphs
Author-email: mskz-3110 <mskz.saito@gmail.com>
Project-URL: Homepage, https://github.com/mskz-3110/graspgraph
Project-URL: Issues, https://github.com/mskz-3110/graspgraph/issues
Classifier: Programming Language :: Python :: 3
Classifier: License :: OSI Approved :: MIT License
Classifier: Operating System :: OS Independent
Requires-Python: >=3.13
License-File: LICENSE
Requires-Dist: plotly
Requires-Dist: numpy
Requires-Dist: kaleido==1.0.0rc0
Requires-Dist: graphviz
Requires-Dist: pydantic
Requires-Dist: pyyaml
Requires-Dist: inflection
Requires-Dist: pdf2image
Requires-Dist: pyemon
